multireplace/__init__.py
multireplace/multireplace.py
multireplace/test_multiplace.py
multireplace-0.0.2.dist-info/LICENSE.md
multireplace-0.0.2.dist-info/METADATA
multireplace-0.0.2.dist-info/WHEEL
multireplace-0.0.2.dist-info/top_level.txt
multireplace-0.0.2.dist-info/RECORD
