Metadata-Version: 2.1
Name: multireplace
Version: 0.0.2
Summary: Method for multi replace in strings
Home-page: https://github.com/Oshten/multireplace
Author: Oshten
License: UNKNOWN
Platform: UNKNOWN
Classifier: Programming Language :: Python :: 3.7
Classifier: License :: OSI Approved :: GNU General Public License v3 (GPLv3)
